csng_invariances/__init__.py
csng_invariances/csng_invariances.py
csng_invariances/src/__init__.py
csng_invariances/src/datasets.py
csng_invariances/src/datasets/__init__.py
csng_invariances/src/datasets/antolik_2016.py
csng_invariances/src/datasets/lurz_2021.py
csng_invariances/src/models/__init__.py
csng_invariances/src/models/discriminator.py
csng_invariances/src/models/generator.py
csng_invariances/src/transforms/__init__.py
csng_invariances/src/transforms/transforms.py
csng_invariances-0.0.4.dist-info/AUTHORS.rst
csng_invariances-0.0.4.dist-info/LICENSE
csng_invariances-0.0.4.dist-info/METADATA
csng_invariances-0.0.4.dist-info/WHEEL
csng_invariances-0.0.4.dist-info/top_level.txt
csng_invariances-0.0.4.dist-info/RECORD
