Metadata-Version: 2.1
Name: csng-invariances
Version: 0.0.4
Summary: Reimplementation of Kovacs 2021: Finding invariances in sensory coding through gradient methods. in PyTorch.
Home-page: https://github.com/leeeeon4/csng_invariances
Author: Leon Michel Gorissen
Author-email: leon.gorissen@rwth-aachen.de
License: MIT license
Keywords: csng_invariances
Platform: UNKNOWN
Classifier: Development Status :: 2 - Pre-Alpha
Classifier: Intended Audience :: Developers
Classifier: License :: OSI Approved :: MIT License
Classifier: Natural Language :: English
Classifier: Programming Language :: Python :: 3.9
Requires-Python: >=3.9
